auto_git_flow/__init__.py
auto_git_flow/gffs.py
auto_git_flow/gfhs.py
auto_git_flow/gfrs.py
auto_git_flow/utils.py
auto_git_flow-1.1.1.dist-info/METADATA
auto_git_flow-1.1.1.dist-info/WHEEL
auto_git_flow-1.1.1.dist-info/entry_points.txt
auto_git_flow-1.1.1.dist-info/top_level.txt
auto_git_flow-1.1.1.dist-info/RECORD
