Metadata-Version: 2.1
Name: auto-git-flow
Version: 1.1.1
Summary: Git flow wrapper to save few lines
Home-page: https://gitlab.com/pypa/sampleproject
Author: Constantin De La Roche
Author-email: cdlr75@gmail.com
License: UNKNOWN
Project-URL: Bug Reports, https://gitlab.com/cdlr75/auto-git-flow/issues
Project-URL: Source, https://gitlab.com/cdlr75/auto-git-flow/
Keywords: git git-flow wrapper
Platform: UNKNOWN
Classifier: Development Status :: 3 - Alpha
Classifier: Intended Audience :: Developers
Classifier: Topic :: Software Development :: Build Tools
Classifier: License :: OSI Approved :: MIT License
Classifier: Programming Language :: Python :: 3
Classifier: Programming Language :: Python :: 3.5
Classifier: Programming Language :: Python :: 3.6
Classifier: Programming Language :: Python :: 3.7
Classifier: Programming Language :: Python :: 3.8
Requires-Python: >=3
Provides-Extra: test
Requires-Dist: asynctest ; extra == 'test'
Requires-Dist: coverage ; extra == 'test'
Requires-Dist: pycodestyle ; extra == 'test'
Requires-Dist: pylint ; extra == 'test'
